CellNeighborEX/DEanalysis.py
CellNeighborEX/__init__.py
CellNeighborEX/__version__.py
CellNeighborEX/categorization.py
CellNeighborEX/neighbors.py
CellNeighborEX/visualization.py
CellNeighborEX-1.0.1.dist-info/LICENSE
CellNeighborEX-1.0.1.dist-info/METADATA
CellNeighborEX-1.0.1.dist-info/WHEEL
CellNeighborEX-1.0.1.dist-info/top_level.txt
CellNeighborEX-1.0.1.dist-info/RECORD
