Metadata-Version: 2.1
Name: CellNeighborEX
Version: 1.0.1
Summary: library for neighbor-dependent gene expression analysis
Home-page: https://github.com/hkim240/CellNeighborEX
Author: Hyobin Kim
Author-email: hbkim20005@gmail.com
License: UNKNOWN
Platform: UNKNOWN
Classifier: Programming Language :: Python :: 3
Classifier: License :: OSI Approved :: MIT License
Classifier: Operating System :: OS Independent
Requires-Python: >=3.8,<3.11
License-File: LICENSE
